blueprintpy/__init__.py
blueprintpy/cli/__init__.py
blueprintpy/cli/cli.py
blueprintpy/cli/config_loader.py
blueprintpy/cli/config_serializer.py
blueprintpy/cli/args_handler/__init__.py
blueprintpy/cli/args_handler/base.py
blueprintpy/cli/args_handler/default.py
blueprintpy/cli/args_handler/exceptions.py
blueprintpy/cli/args_handler/resolver/__init__.py
blueprintpy/cli/args_handler/resolver/base.py
blueprintpy/cli/args_handler/resolver/lists.py
blueprintpy/cli/args_handler/resolver/numbers.py
blueprintpy/cli/args_handler/resolver/string.py
blueprintpy/core/__init__.py
blueprintpy/core/argument.py
blueprintpy/core/config.py
blueprintpy/core/content.py
blueprintpy/core/content_builder.py
blueprintpy/core/content_extractor.py
blueprintpy/core/prepared_content.py
blueprintpy/internal_templates/__init__.py
blueprintpy/internal_templates/avr/CMakeLists_app.txt.j2
blueprintpy/internal_templates/avr/CMakeLists_app_src.txt.j2
blueprintpy/internal_templates/avr/README.md.j2
blueprintpy/internal_templates/avr/__init__.py
blueprintpy/internal_templates/avr/app.gitignore
blueprintpy/internal_templates/avr/avr_toolchain.cmake
blueprintpy/internal_templates/avr/main.cpp.j2
blueprintpy/internal_templates/avr/root.gitignore
blueprintpy/internal_templates/avr/settings.json
blueprintpy/internal_templates/avr/template.json
blueprintpy/internal_templates/cmake/CMakeLists_cli.j2
blueprintpy/internal_templates/cmake/CMakeLists_root.j2
blueprintpy/internal_templates/cmake/CMakeLists_src.j2
blueprintpy/internal_templates/cmake/CMakeLists_tests.j2
blueprintpy/internal_templates/cmake/README.md.j2
blueprintpy/internal_templates/cmake/__init__.py
blueprintpy/internal_templates/cmake/main.cpp.j2
blueprintpy/internal_templates/cmake/project.cpp.j2
blueprintpy/internal_templates/cmake/project.hpp.j2
blueprintpy/internal_templates/cmake/template.json
blueprintpy/internal_templates/cmake/test_project.cpp.j2
blueprintpy/internal_templates/default/README.md.j2
blueprintpy-2.2.0.dist-info/METADATA
blueprintpy-2.2.0.dist-info/WHEEL
blueprintpy-2.2.0.dist-info/entry_points.txt
blueprintpy-2.2.0.dist-info/top_level.txt
blueprintpy-2.2.0.dist-info/RECORD
