Metadata-Version: 2.1
Name: blueprintpy
Version: 2.2.0
Summary: Python パッケージテンプレート展開ユーティリティ
Home-page: https://github.com/Enchan1207/blueprintpy
Author: Enchan1207
Author-email: enchant0130@gmail.com
License: MIT
Project-URL: Documentation, https://enchan1207.github.io/blueprintpy/index.html
Requires-Dist: Jinja2 (>=3.0.1)
